{
  "id": "finvarr",
  "name": "Finvarr",
  "faction": "Guardian",
  "source": "Characters/finvarr/",
  "iconReference": "icons.json",
  "iconPlaceholderFormat": "{icon_id}",
  "extractionNotes": [
    "Every skill (plot, clash, and ultimate) is preceded on the card by a target icon from icons.json skillIcons: skill_self, skill_friendly, skill_area, or skill_enemy. Stored as the skillIcon field.",
    "Skill range / accuracy / damage are stored only in statProfiles. Use figuresInHex \"-\" when the card shows a single stat row; use 1, 2, or 3 when multiple rows match follower figures in the hex (max 3).",
    "Champion and follower stats always use plotSpeed and clashSpeed (never a single speed field), even when both values are the same.",
    "Follower stats are plotSpeed, clashSpeed, dodge, protection, and health from the stat row on the follower card. Unit count (top-right icon) is stored separately as units.",
    "If card text says \"Must target a follower\" or \"Must target a champion\", remove it from text and store as mustTarget (follower, champion, or -).",
    "Icon-only boon effects: skill_self → \"Gain {boon_id}\", skill_friendly → \"Grant {boon_id}\". Icon-only blight or \"Hit Effect:\" blight → \"Inflict {blight_id}\"."
  ],
  "champion": {
    "stats": {
      "plotSpeed": "2",
      "clashSpeed": "3",
      "dodge": "4",
      "protection": "3",
      "health": "5"
    },
    "factionTrait": {
      "name": "Guardian Champion",
      "text": "A guardian moves the turn token +1 step when they have their banner on an objective hex during the end phase."
    },
    "uniqueTraits": [
      {
        "name": "Banner Warden",
        "text": "If Finvarr is on an objective hex, his skills have +2 {accuracy_die}."
      }
    ],
    "ultimate": {
      "name": "Phantom Banners",
      "skillIcon": "skill_area",
      "mustTarget": "-",
      "text": "Choose any number of friendly banners within range. Place them on objective hexes within range.",
      "statProfiles": [
        {
          "figuresInHex": "-",
          "range": "4",
          "accuracy": "-",
          "damage": "-"
        }
      ]
    },
    "plotSkills": [
      {
        "name": "Poised to Strike",
        "skillIcon": "skill_self",
        "mustTarget": "-",
        "text": "Gain {move_boon}",
        "statProfiles": [
          {
            "figuresInHex": "-",
            "range": "-",
            "accuracy": "-",
            "damage": "-"
          }
        ]
      },
      {
        "name": "Shadow Ward",
        "skillIcon": "skill_enemy",
        "mustTarget": "-",
        "text": "Hit Effect: Move target up to 1 hex.",
        "statProfiles": [
          {
            "figuresInHex": "-",
            "range": "2",
            "accuracy": "5",
            "damage": "-"
          }
        ]
      }
    ],
    "clashSkills": [
      {
        "name": "Mirage",
        "skillIcon": "skill_area",
        "mustTarget": "-",
        "text": "Choose a friendly banner within 2 hexes of Finvarr. Place it on an objective hex that is 1 hex away from its current hex.",
        "statProfiles": [
          {
            "figuresInHex": "-",
            "range": "-",
            "accuracy": "-",
            "damage": "-"
          }
        ]
      },
      {
        "name": "Void Weapon",
        "skillIcon": "skill_self",
        "mustTarget": "-",
        "text": "Gain {damage_die_boon}",
        "statProfiles": [
          {
            "figuresInHex": "-",
            "range": "-",
            "accuracy": "-",
            "damage": "-"
          }
        ]
      },
      {
        "name": "Life Blade",
        "skillIcon": "skill_enemy",
        "mustTarget": "-",
        "text": "Hit Effect: Remove up to 1 of Finvarr's wounds.",
        "statProfiles": [
          {
            "figuresInHex": "-",
            "range": "1",
            "accuracy": "4",
            "damage": "5"
          }
        ]
      }
    ]
  },
  "followers": {
    "name": "Shadow Sentinels",
    "units": 3,
    "size": "small",
    "stats": {
      "plotSpeed": "2",
      "clashSpeed": "3",
      "dodge": "4",
      "protection": "2",
      "health": "1"
    },
    "traits": [
      {
        "name": "Shadow Step",
        "text": "If the Shadow Sentinels do not make an advance action during their activation, each Shadow Sentinel may move up to 1 hex when the activation ends."
      }
    ],
    "plotSkills": [
      {
        "name": "Protect",
        "skillIcon": "skill_friendly",
        "mustTarget": "-",
        "text": "Grant {protection_boon}",
        "statProfiles": [
          {
            "figuresInHex": "-",
            "range": "1",
            "accuracy": "-",
            "damage": "-"
          }
        ]
      },
      {
        "name": "Shadow Snare",
        "skillIcon": "skill_enemy",
        "mustTarget": "-",
        "text": "Inflict {move_blight}",
        "statProfiles": [
          {
            "figuresInHex": 1,
            "range": "1",
            "accuracy": "4",
            "damage": "-"
          },
          {
            "figuresInHex": 2,
            "range": "1",
            "accuracy": "5",
            "damage": "-"
          },
          {
            "figuresInHex": 3,
            "range": "1",
            "accuracy": "5",
            "damage": "-"
          }
        ]
      }
    ],
    "clashSkills": [
      {
        "name": "Void Weapon",
        "skillIcon": "skill_self",
        "mustTarget": "-",
        "text": "Gain {damage_die_boon}",
        "statProfiles": [
          {
            "figuresInHex": "-",
            "range": "-",
            "accuracy": "-",
            "damage": "-"
          }
        ]
      },
      {
        "name": "Life Trade",
        "skillIcon": "skill_enemy",
        "mustTarget": "-",
        "text": "If this skill knocks out an enemy while the Shadow Sentinels are below their maximum unit size, add 1 Shadow Sentinel to this hex.",
        "statProfiles": [
          {
            "figuresInHex": 1,
            "range": "1",
            "accuracy": "4",
            "damage": "4"
          },
          {
            "figuresInHex": 2,
            "range": "1",
            "accuracy": "5",
            "damage": "5"
          },
          {
            "figuresInHex": 3,
            "range": "1",
            "accuracy": "5",
            "damage": "5"
          }
        ]
      }
    ]
  }
}