{
  "id": "lorsann",
  "name": "Lorsann",
  "faction": "Slayer",
  "source": "Characters/lorsann/",
  "iconReference": "icons.json",
  "iconPlaceholderFormat": "{icon_id}",
  "extractionNotes": [
    "Every skill (plot, clash, and ultimate) is preceded on the card by a target icon from icons.json skillIcons: skill_self, skill_friendly, skill_area, or skill_enemy. Stored as the skillIcon field.",
    "Skill range / accuracy / damage are stored only in statProfiles. Use figuresInHex \"-\" when the card shows a single stat row; use 1, 2, or 3 when multiple rows match follower figures in the hex (max 3).",
    "Champion and follower stats always use plotSpeed and clashSpeed (never a single speed field), even when both values are the same.",
    "Follower stats are plotSpeed, clashSpeed, dodge, protection, and health from the stat row on the follower card. Unit count (top-right icon) is stored separately as units.",
    "If card text says \"Must target a follower\" or \"Must target a champion\", remove it from text and store as mustTarget (follower, champion, or -).",
    "Icon-only boon effects: skill_self → \"Gain {boon_id}\", skill_friendly → \"Grant {boon_id}\". Icon-only blight or \"Hit Effect:\" blight → \"Inflict {blight_id}\"."
  ],
  "champion": {
    "stats": {
      "plotSpeed": "2",
      "clashSpeed": "3",
      "dodge": "4",
      "protection": "1",
      "health": "6"
    },
    "factionTrait": {
      "name": "Slayer Champion",
      "text": "A slayer moves the turn token +1 step when they knock out an enemy champion."
    },
    "uniqueTraits": [
      {
        "name": "Shoot and Scoot",
        "text": "After Lorsann uses a skill that inflicts 1 or more wounds, she may move up to 1 hex."
      }
    ],
    "ultimate": {
      "name": "Deathblow",
      "skillIcon": "skill_enemy",
      "mustTarget": "-",
      "text": "Hit Effect: The target gains 2 wounds.",
      "statProfiles": [
        {
          "figuresInHex": "-",
          "range": "3",
          "accuracy": "6",
          "damage": "-"
        }
      ]
    },
    "plotSkills": [
      {
        "name": "Field Instruction",
        "skillIcon": "skill_friendly",
        "mustTarget": "-",
        "text": "Grant {accuracy_die_boon}",
        "statProfiles": [
          {
            "figuresInHex": "-",
            "range": "2",
            "accuracy": "-",
            "damage": "-"
          }
        ]
      },
      {
        "name": "Fairy Fire",
        "skillIcon": "skill_enemy",
        "mustTarget": "-",
        "text": "Hit Effect: Inflict {dodge_blight}.",
        "statProfiles": [
          {
            "figuresInHex": "-",
            "range": "3",
            "accuracy": "5",
            "damage": "-"
          }
        ]
      }
    ],
    "clashSkills": [
      {
        "name": "Piercing Shot",
        "skillIcon": "skill_enemy",
        "mustTarget": "-",
        "text": "Hit Effect: The target gains 1 wound.",
        "statProfiles": [
          {
            "figuresInHex": "-",
            "range": "3",
            "accuracy": "5",
            "damage": "-"
          }
        ]
      },
      {
        "name": "Mystic Arrow",
        "skillIcon": "skill_enemy",
        "mustTarget": "-",
        "text": "After the mystic arrow damage roll, make a 5 {damage} damage roll against the target.",
        "statProfiles": [
          {
            "figuresInHex": "-",
            "range": "3",
            "accuracy": "3",
            "damage": "5"
          }
        ]
      },
      {
        "name": "Snipe",
        "skillIcon": "skill_enemy",
        "mustTarget": "-",
        "text": "",
        "statProfiles": [
          {
            "figuresInHex": "-",
            "range": "3",
            "accuracy": "8",
            "damage": "4"
          }
        ]
      }
    ]
  },
  "followers": {
    "name": "Mistwood Rangers",
    "units": 3,
    "stats": {
      "plotSpeed": "2",
      "clashSpeed": "3",
      "dodge": "3",
      "protection": "1",
      "health": "1"
    },
    "traits": [
      {
        "name": "Kill Shot",
        "text": "When the target is a wounded enemy champion, the Mistwood Rangers' skills have +1 {damage}."
      }
    ],
    "plotSkills": [
      {
        "name": "Blur",
        "skillIcon": "skill_self",
        "mustTarget": "-",
        "text": "Gain {dodge_boon}",
        "statProfiles": [
          {
            "figuresInHex": "-",
            "range": "-",
            "accuracy": "-",
            "damage": "-"
          }
        ]
      },
      {
        "name": "Faerie Fire",
        "skillIcon": "skill_enemy",
        "mustTarget": "-",
        "text": "Hit Effect: Inflict {dodge_blight}.",
        "statProfiles": [
          {
            "figuresInHex": 1,
            "range": "3",
            "accuracy": "3",
            "damage": "-"
          },
          {
            "figuresInHex": 2,
            "range": "3",
            "accuracy": "4",
            "damage": "-"
          },
          {
            "figuresInHex": 3,
            "range": "3",
            "accuracy": "5",
            "damage": "-"
          }
        ]
      }
    ],
    "clashSkills": [
      {
        "name": "Aim",
        "skillIcon": "skill_self",
        "mustTarget": "-",
        "text": "Gain {accuracy_die_boon}",
        "statProfiles": [
          {
            "figuresInHex": "-",
            "range": "-",
            "accuracy": "-",
            "damage": "-"
          }
        ]
      },
      {
        "name": "Fire",
        "skillIcon": "skill_enemy",
        "mustTarget": "-",
        "text": "",
        "statProfiles": [
          {
            "figuresInHex": 1,
            "range": "3",
            "accuracy": "3",
            "damage": "3"
          },
          {
            "figuresInHex": 2,
            "range": "3",
            "accuracy": "4",
            "damage": "4"
          },
          {
            "figuresInHex": 3,
            "range": "3",
            "accuracy": "5",
            "damage": "5"
          }
        ]
      }
    ]
  }
}
